{
  "$type": "MigrationTools.Processors.WorkItemTrackingProcessorOptions, MigrationTools",
  "ReplayRevisions": true,
  "PrefixProjectToNodes": false,
  "CollapseRevisions": false,
  "WorkItemCreateRetryLimit": 5,
  "Enabled": true,
  "Endpoints": null,
  "ProcessorEnrichers": [
    {
      "$type": "MigrationTools.Enrichers.PauseAfterEachItemOptions, MigrationTools",
      "Enabled": true
    },
    {
      "$type": "MigrationTools.Enrichers.AppendMigrationToolSignatureFooterOptions, MigrationTools",
      "Enabled": true
    }
  ]
}